{"id":"t74pbdij7nv4kvs6gx3bgcc","title":"Errors","desc":"","updated":1654340353834,"created":1654340101370,"custom":{},"fname":"lang.cljs.clojure-lsp.errors","type":"note","vault":{"fsPath":"vault"},"contentHash":"75dbbcf456ca6a6d4f247ca9b147344c","links":[{"type":"wiki","from":{"fname":"lang.cljs.clojure-lsp.errors","id":"t74pbdij7nv4kvs6gx3bgcc","vaultName":"vault"},"value":"powershell.versions","alias":"powershell.versions","position":{"start":{"line":4,"column":49,"offset":85},"end":{"line":4,"column":72,"offset":108},"indent":[]},"xvault":false,"sameFile":false,"to":{"fname":"powershell.versions"}},{"type":"wiki","from":{"fname":"lang.cljs.clojure-lsp.errors","id":"t74pbdij7nv4kvs6gx3bgcc","vaultName":"vault"},"value":"powershell.versions.7.1","alias":"powershell.versions.7.1","position":{"start":{"line":4,"column":107,"offset":143},"end":{"line":4,"column":134,"offset":170},"indent":[]},"xvault":false,"sameFile":false,"to":{"fname":"powershell.versions.7.1"}}],"anchors":{"error-cannot-run-program-pwsh":{"type":"header","text":"error cannot run program \"pwsh\"","value":"error-cannot-run-program-pwsh","line":8,"column":0,"depth":2}},"children":[],"parent":"pnvztdqzozf3rov3kws0554","data":{}}
