{"id":"yf8d4qvk9xuqytu2nb2eh5y","title":"Filetypes","desc":"","updated":1646453899096,"created":1646447307486,"custom":{},"fname":"vim.filetypes","type":"note","vault":{"fsPath":"vault"},"contentHash":"04499686b62c36df9183d96aabc2047d","links":[{"from":{"fname":"vim.plugins.treesitter","vaultName":"vault"},"type":"backlink","position":{"start":{"line":33,"column":1,"offset":940},"end":{"line":33,"column":115,"offset":1054},"indent":[]},"value":"vim.filetypes"}],"anchors":{"list-of-filetypes":{"type":"header","text":"List of filetypes","value":"list-of-filetypes","line":8,"column":0,"depth":2},"get-the-filetype":{"type":"header","text":"Get the filetype","value":"get-the-filetype","line":12,"column":0,"depth":2},"set-the-filetype":{"type":"header","text":"Set the filetype","value":"set-the-filetype","line":18,"column":0,"depth":2},"cc":{"type":"header","text":"C/C++","value":"cc","line":22,"column":0,"depth":2},"vim-recognising-header-files-as-c-instead-of-c":{"type":"header","text":"Vim recognising header files as C++ instead of C","value":"vim-recognising-header-files-as-c-instead-of-c","line":24,"column":0,"depth":3},"filetype-detection-for-h-files-as-c-with-doxygen":{"type":"header","text":"Filetype detection for .h files as C with Doxygen","value":"filetype-detection-for-h-files-as-c-with-doxygen","line":32,"column":0,"depth":3}},"children":[],"parent":"5acd228c-faa2-4c6c-8fed-6abd55a1e819","data":{}}
